pythoncloudlogger/__init__.py
pythoncloudlogger/formatters.py
pythoncloudlogger/index.py
python_cloud_logger-0.1.1.dist-info/LICENSE
python_cloud_logger-0.1.1.dist-info/METADATA
python_cloud_logger-0.1.1.dist-info/WHEEL
python_cloud_logger-0.1.1.dist-info/top_level.txt
python_cloud_logger-0.1.1.dist-info/RECORD
