Metadata-Version: 2.1
Name: python-cloud-logger
Version: 0.1.1
Summary: A logger with thread local storage for logging context in all logs without repeating the code
Home-page: https://github.com/vasudevan-palani/python-cloud-logger
Author: Vasudevan Palani
Author-email: vasudevan.palani@gmail.com
License: TBD
Platform: UNKNOWN
